PyUniProt-0.0.10.dist-info/DESCRIPTION.rst
PyUniProt-0.0.10.dist-info/METADATA
PyUniProt-0.0.10.dist-info/RECORD
PyUniProt-0.0.10.dist-info/WHEEL
PyUniProt-0.0.10.dist-info/entry_points.txt
PyUniProt-0.0.10.dist-info/metadata.json
PyUniProt-0.0.10.dist-info/top_level.txt
pyuniprot/__init__.py
pyuniprot/cli.py
pyuniprot/constants.py
pyuniprot/manager/__init__.py
pyuniprot/manager/database.py
pyuniprot/manager/defaults.py
pyuniprot/manager/make_json_serializable.py
pyuniprot/manager/models.py
pyuniprot/manager/query.py
pyuniprot/webserver/__init__.py
pyuniprot/webserver/web.py
