Metadata-Version: 2.0
Name: PyUniProt
Version: 0.0.10
Summary: Importing and querying UniProt
Home-page: https://github.com/cebel/pyuniprot
Author: Christian Ebeling
Author-email: christian.ebeling@scai.fraunhofer.de
License: Apache 2.0 License
Keywords: UniProt,Database,Protein
Platform: UNKNOWN
Classifier: Development Status :: 5 - Production/Stable
Classifier: Operating System :: OS Independent
Classifier: Environment :: Console
Classifier: Programming Language :: Python
Classifier: Programming Language :: Python :: 2.7
Classifier: Programming Language :: Python :: 3.4
Classifier: Programming Language :: Python :: 3.5
Classifier: Programming Language :: Python :: 3.6
Classifier: Intended Audience :: Developers
Classifier: License :: OSI Approved :: MIT License
Classifier: Topic :: Database
Classifier: Topic :: Scientific/Engineering :: Bio-Informatics
Requires-Dist: click
Requires-Dist: configparser
Requires-Dist: flasgger
Requires-Dist: pandas
Requires-Dist: passlib
Requires-Dist: pymysql
Requires-Dist: requests
Requires-Dist: sqlalchemy
Requires-Dist: tqdm
Requires-Dist: wtforms
